[
  {
    "('Date', '')":"2024-11-14",
    "('Close', '1038.HK')":49.8164596558,
    "('High', '1038.HK')":50.5770155443,
    "('Low', '1038.HK')":49.5312480243,
    "('Open', '1038.HK')":50.4819437916,
    "('Volume', '1038.HK')":2128651
  },
  {
    "('Date', '')":"2024-11-15",
    "('Close', '1038.HK')":50.9097557068,
    "('High', '1038.HK')":51.8604514385,
    "('Low', '1038.HK')":49.436178048,
    "('Open', '1038.HK')":49.436178048,
    "('Volume', '1038.HK')":1894902
  },
  {
    "('Date', '')":"2024-11-18",
    "('Close', '1038.HK')":50.8622245789,
    "('High', '1038.HK')":51.3851065361,
    "('Low', '1038.HK')":50.4344107496,
    "('Open', '1038.HK')":50.9572927069,
    "('Volume', '1038.HK')":826004
  },
  {
    "('Date', '')":"2024-11-19",
    "('Close', '1038.HK')":51.480178833,
    "('High', '1038.HK')":51.7653868466,
    "('Low', '1038.HK')":50.577017101,
    "('Open', '1038.HK')":50.8622251146,
    "('Volume', '1038.HK')":1296469
  },
  {
    "('Date', '')":"2024-11-20",
    "('Close', '1038.HK')":51.2900390625,
    "('High', '1038.HK')":51.5277130122,
    "('Low', '1038.HK')":50.8622252278,
    "('Open', '1038.HK')":51.0523651128,
    "('Volume', '1038.HK')":937658
  },
  {
    "('Date', '')":"2024-11-21",
    "('Close', '1038.HK')":51.5752449036,
    "('High', '1038.HK')":51.6703130288,
    "('Low', '1038.HK')":50.814689022,
    "('Open', '1038.HK')":50.9572912098,
    "('Volume', '1038.HK')":1529366
  },
  {
    "('Date', '')":"2024-11-22",
    "('Close', '1038.HK')":50.719619751,
    "('High', '1038.HK')":51.7653873125,
    "('Low', '1038.HK')":50.5770175562,
    "('Open', '1038.HK')":51.0998995237,
    "('Volume', '1038.HK')":1788607
  },
  {
    "('Date', '')":"2024-11-25",
    "('Close', '1038.HK')":51.2900390625,
    "('High', '1038.HK')":51.4326412563,
    "('Low', '1038.HK')":50.5770172135,
    "('Open', '1038.HK')":51.0523651128,
    "('Volume', '1038.HK')":3181142
  },
  {
    "('Date', '')":"2024-11-26",
    "('Close', '1038.HK')":51.5277137756,
    "('High', '1038.HK')":51.5277137756,
    "('Low', '1038.HK')":51.1949680652,
    "('Open', '1038.HK')":51.2900398225,
    "('Volume', '1038.HK')":1475358
  },
  {
    "('Date', '')":"2024-11-27",
    "('Close', '1038.HK')":51.0048294067,
    "('High', '1038.HK')":52.0030592379,
    "('Low', '1038.HK')":50.3393416438,
    "('Open', '1038.HK')":51.4326396011,
    "('Volume', '1038.HK')":4095132
  },
  {
    "('Date', '')":"2024-11-28",
    "('Close', '1038.HK')":51.7178497314,
    "('High', '1038.HK')":51.7178497314,
    "('Low', '1038.HK')":50.5294800559,
    "('Open', '1038.HK')":51.1949641729,
    "('Volume', '1038.HK')":1606929
  },
  {
    "('Date', '')":"2024-11-29",
    "('Close', '1038.HK')":50.9572944641,
    "('High', '1038.HK')":52.050596107,
    "('Low', '1038.HK')":50.5770183124,
    "('Open', '1038.HK')":52.050596107,
    "('Volume', '1038.HK')":1562819
  },
  {
    "('Date', '')":"2024-12-02",
    "('Close', '1038.HK')":50.8622245789,
    "('High', '1038.HK')":51.1949666535,
    "('Low', '1038.HK')":50.6245506322,
    "('Open', '1038.HK')":50.9572927069,
    "('Volume', '1038.HK')":1491853
  },
  {
    "('Date', '')":"2024-12-03",
    "('Close', '1038.HK')":52.4784088135,
    "('High', '1038.HK')":52.5734769427,
    "('Low', '1038.HK')":50.6245512807,
    "('Open', '1038.HK')":50.8622252304,
    "('Volume', '1038.HK')":3046516
  },
  {
    "('Date', '')":"2024-12-04",
    "('Close', '1038.HK')":51.1474304199,
    "('High', '1038.HK')":52.3833341647,
    "('Low', '1038.HK')":50.7671542974,
    "('Open', '1038.HK')":51.9555239802,
    "('Volume', '1038.HK')":2440566
  },
  {
    "('Date', '')":"2024-12-05",
    "('Close', '1038.HK')":51.7178497314,
    "('High', '1038.HK')":51.7178497314,
    "('Low', '1038.HK')":50.6245481793,
    "('Open', '1038.HK')":51.1474301112,
    "('Volume', '1038.HK')":1085510
  },
  {
    "('Date', '')":"2024-12-06",
    "('Close', '1038.HK')":51.4326400757,
    "('High', '1038.HK')":52.0030597177,
    "('Low', '1038.HK')":51.2900378851,
    "('Open', '1038.HK')":51.71785171,
    "('Volume', '1038.HK')":2402314
  },
  {
    "('Date', '')":"2024-12-09",
    "('Close', '1038.HK')":51.480178833,
    "('High', '1038.HK')":52.0030607958,
    "('Low', '1038.HK')":51.2425048839,
    "('Open', '1038.HK')":51.480178833,
    "('Volume', '1038.HK')":1675766
  },
  {
    "('Date', '')":"2024-12-10",
    "('Close', '1038.HK')":51.2425041199,
    "('High', '1038.HK')":52.098128148,
    "('Low', '1038.HK')":51.0998983019,
    "('Open', '1038.HK')":51.5277121293,
    "('Volume', '1038.HK')":2925615
  },
  {
    "('Date', '')":"2024-12-11",
    "('Close', '1038.HK')":51.0523643494,
    "('High', '1038.HK')":51.5752463055,
    "('Low', '1038.HK')":50.8146904033,
    "('Open', '1038.HK')":51.2425042316,
    "('Volume', '1038.HK')":1294274
  },
  {
    "('Date', '')":"2024-12-12",
    "('Close', '1038.HK')":50.5294799805,
    "('High', '1038.HK')":51.3851039696,
    "('Low', '1038.HK')":50.5294799805,
    "('Open', '1038.HK')":51.0523619116,
    "('Volume', '1038.HK')":2054133
  },
  {
    "('Date', '')":"2024-12-13",
    "('Close', '1038.HK')":50.4344100952,
    "('High', '1038.HK')":50.8622239189,
    "('Low', '1038.HK')":50.1492020883,
    "('Open', '1038.HK')":50.4819441586,
    "('Volume', '1038.HK')":1817233
  },
  {
    "('Date', '')":"2024-12-16",
    "('Close', '1038.HK')":51.0048294067,
    "('High', '1038.HK')":51.0998975329,
    "('Low', '1038.HK')":50.3393416438,
    "('Open', '1038.HK')":50.8622235909,
    "('Volume', '1038.HK')":1425322
  },
  {
    "('Date', '')":"2024-12-17",
    "('Close', '1038.HK')":50.4344100952,
    "('High', '1038.HK')":51.0523637991,
    "('Low', '1038.HK')":50.2442702151,
    "('Open', '1038.HK')":51.0048297357,
    "('Volume', '1038.HK')":1047818
  },
  {
    "('Date', '')":"2024-12-18",
    "('Close', '1038.HK')":51.2900390625,
    "('High', '1038.HK')":51.6227811414,
    "('Low', '1038.HK')":50.4344113931,
    "('Open', '1038.HK')":50.4344113931,
    "('Volume', '1038.HK')":1436267
  },
  {
    "('Date', '')":"2024-12-19",
    "('Close', '1038.HK')":51.0048294067,
    "('High', '1038.HK')":51.5752454169,
    "('Low', '1038.HK')":50.719617775,
    "('Open', '1038.HK')":50.8622235909,
    "('Volume', '1038.HK')":1621352
  },
  {
    "('Date', '')":"2024-12-20",
    "('Close', '1038.HK')":51.5277137756,
    "('High', '1038.HK')":52.1456638779,
    "('Low', '1038.HK')":50.7671578508,
    "('Open', '1038.HK')":50.7671578508,
    "('Volume', '1038.HK')":3184745
  },
  {
    "('Date', '')":"2024-12-23",
    "('Close', '1038.HK')":53.1438941956,
    "('High', '1038.HK')":53.6667761359,
    "('Low', '1038.HK')":51.5277106855,
    "('Open', '1038.HK')":51.5277106855,
    "('Volume', '1038.HK')":3734006
  },
  {
    "('Date', '')":"2024-12-24",
    "('Close', '1038.HK')":53.8093795776,
    "('High', '1038.HK')":53.8093795776,
    "('Low', '1038.HK')":53.8093795776,
    "('Open', '1038.HK')":53.8093795776,
    "('Volume', '1038.HK')":0
  },
  {
    "('Date', '')":"2024-12-27",
    "('Close', '1038.HK')":54.1421279907,
    "('High', '1038.HK')":54.1896620567,
    "('Low', '1038.HK')":53.1914321652,
    "('Open', '1038.HK')":53.3815720556,
    "('Volume', '1038.HK')":1914347
  },
  {
    "('Date', '')":"2024-12-30",
    "('Close', '1038.HK')":54.7600746155,
    "('High', '1038.HK')":55.1403543721,
    "('Low', '1038.HK')":53.9519846658,
    "('Open', '1038.HK')":54.0470527917,
    "('Volume', '1038.HK')":2349732
  },
  {
    "('Date', '')":"2024-12-31",
    "('Close', '1038.HK')":54.9026794434,
    "('High', '1038.HK')":54.9026794434,
    "('Low', '1038.HK')":54.9026794434,
    "('Open', '1038.HK')":54.9026794434,
    "('Volume', '1038.HK')":0
  },
  {
    "('Date', '')":"2025-01-02",
    "('Close', '1038.HK')":53.6667785645,
    "('High', '1038.HK')":54.9026823775,
    "('Low', '1038.HK')":53.3815705502,
    "('Open', '1038.HK')":54.8551483129,
    "('Volume', '1038.HK')":1081315
  },
  {
    "('Date', '')":"2025-01-03",
    "('Close', '1038.HK')":53.7143096924,
    "('High', '1038.HK')":53.9044495671,
    "('Low', '1038.HK')":53.4291016937,
    "('Open', '1038.HK')":53.6192415684,
    "('Volume', '1038.HK')":1216889
  },
  {
    "('Date', '')":"2025-01-06",
    "('Close', '1038.HK')":54.2847290039,
    "('High', '1038.HK')":54.4273348253,
    "('Low', '1038.HK')":53.3340331991,
    "('Open', '1038.HK')":53.3340331991,
    "('Volume', '1038.HK')":1462239
  },
  {
    "('Date', '')":"2025-01-07",
    "('Close', '1038.HK')":53.4766387939,
    "('High', '1038.HK')":54.0470548238,
    "('Low', '1038.HK')":53.191430779,
    "('Open', '1038.HK')":53.8569185649,
    "('Volume', '1038.HK')":1086061
  },
  {
    "('Date', '')":"2025-01-08",
    "('Close', '1038.HK')":52.9537582397,
    "('High', '1038.HK')":53.9519881318,
    "('Low', '1038.HK')":52.6210125246,
    "('Open', '1038.HK')":53.0488263717,
    "('Volume', '1038.HK')":1040337
  },
  {
    "('Date', '')":"2025-01-09",
    "('Close', '1038.HK')":53.0963592529,
    "('High', '1038.HK')":53.5241730905,
    "('Low', '1038.HK')":52.8586853017,
    "('Open', '1038.HK')":53.1914310094,
    "('Volume', '1038.HK')":961841
  },
  {
    "('Date', '')":"2025-01-10",
    "('Close', '1038.HK')":53.3340339661,
    "('High', '1038.HK')":53.9519876987,
    "('Low', '1038.HK')":52.9537578146,
    "('Open', '1038.HK')":53.0963600114,
    "('Volume', '1038.HK')":930312
  },
  {
    "('Date', '')":"2025-01-13",
    "('Close', '1038.HK')":51.3851051331,
    "('High', '1038.HK')":53.3340307169,
    "('Low', '1038.HK')":51.3375710704,
    "('Open', '1038.HK')":53.3340307169,
    "('Volume', '1038.HK')":2106556
  },
  {
    "('Date', '')":"2025-01-14",
    "('Close', '1038.HK')":50.8622245789,
    "('High', '1038.HK')":51.6703145468,
    "('Low', '1038.HK')":50.7196187602,
    "('Open', '1038.HK')":51.3375724721,
    "('Volume', '1038.HK')":2328402
  },
  {
    "('Date', '')":"2025-01-15",
    "('Close', '1038.HK')":51.480178833,
    "('High', '1038.HK')":51.575246962,
    "('Low', '1038.HK')":50.9097591791,
    "('Open', '1038.HK')":50.9097591791,
    "('Volume', '1038.HK')":1536692
  },
  {
    "('Date', '')":"2025-01-16",
    "('Close', '1038.HK')":51.6227798462,
    "('High', '1038.HK')":52.0030596068,
    "('Low', '1038.HK')":51.3375718391,
    "('Open', '1038.HK')":51.5277117194,
    "('Volume', '1038.HK')":1886107
  },
  {
    "('Date', '')":"2025-01-17",
    "('Close', '1038.HK')":52.1931991577,
    "('High', '1038.HK')":52.7160811052,
    "('Low', '1038.HK')":51.2425033889,
    "('Open', '1038.HK')":51.7178512733,
    "('Volume', '1038.HK')":2280401
  },
  {
    "('Date', '')":"2025-01-20",
    "('Close', '1038.HK')":52.1456642151,
    "('High', '1038.HK')":52.8111520136,
    "('Low', '1038.HK')":51.62278224,
    "('Open', '1038.HK')":52.7160838824,
    "('Volume', '1038.HK')":1344517
  },
  {
    "('Date', '')":"2025-01-21",
    "('Close', '1038.HK')":51.7178497314,
    "('High', '1038.HK')":52.9537534687,
    "('Low', '1038.HK')":51.7178497314,
    "('Open', '1038.HK')":52.9537534687,
    "('Volume', '1038.HK')":1275572
  },
  {
    "('Date', '')":"2025-01-22",
    "('Close', '1038.HK')":51.2425041199,
    "('High', '1038.HK')":52.0030600204,
    "('Low', '1038.HK')":51.2425041199,
    "('Open', '1038.HK')":52.0030600204,
    "('Volume', '1038.HK')":1445703
  },
  {
    "('Date', '')":"2025-01-23",
    "('Close', '1038.HK')":51.1474304199,
    "('High', '1038.HK')":51.7653841056,
    "('Low', '1038.HK')":51.0523622959,
    "('Open', '1038.HK')":51.2425021705,
    "('Volume', '1038.HK')":1827137
  },
  {
    "('Date', '')":"2025-01-24",
    "('Close', '1038.HK')":51.907989502,
    "('High', '1038.HK')":52.3833374044,
    "('Low', '1038.HK')":51.0048313885,
    "('Open', '1038.HK')":51.7653873072,
    "('Volume', '1038.HK')":1577904
  },
  {
    "('Date', '')":"2025-01-27",
    "('Close', '1038.HK')":51.1949653625,
    "('High', '1038.HK')":51.9079871845,
    "('Low', '1038.HK')":51.0998972369,
    "('Open', '1038.HK')":51.9079871845,
    "('Volume', '1038.HK')":1524558
  },
  {
    "('Date', '')":"2025-01-28",
    "('Close', '1038.HK')":50.4819450378,
    "('High', '1038.HK')":50.4819450378,
    "('Low', '1038.HK')":50.4819450378,
    "('Open', '1038.HK')":50.4819450378,
    "('Volume', '1038.HK')":0
  },
  {
    "('Date', '')":"2025-02-03",
    "('Close', '1038.HK')":50.1492042542,
    "('High', '1038.HK')":50.6720862272,
    "('Low', '1038.HK')":49.721390412,
    "('Open', '1038.HK')":49.9115303003,
    "('Volume', '1038.HK')":1876020
  },
  {
    "('Date', '')":"2025-02-04",
    "('Close', '1038.HK')":50.1967353821,
    "('High', '1038.HK')":51.2900369563,
    "('Low', '1038.HK')":49.6738534396,
    "('Open', '1038.HK')":50.3868752593,
    "('Volume', '1038.HK')":2521021
  },
  {
    "('Date', '')":"2025-02-05",
    "('Close', '1038.HK')":49.4361801147,
    "('High', '1038.HK')":50.3393418229,
    "('Low', '1038.HK')":49.3411119882,
    "('Open', '1038.HK')":49.9115280005,
    "('Volume', '1038.HK')":2041351
  },
  {
    "('Date', '')":"2025-02-06",
    "('Close', '1038.HK')":49.8639945984,
    "('High', '1038.HK')":50.00659679,
    "('Low', '1038.HK')":49.293574952,
    "('Open', '1038.HK')":49.6263206524,
    "('Volume', '1038.HK')":1314414
  },
  {
    "('Date', '')":"2025-02-07",
    "('Close', '1038.HK')":49.2460403442,
    "('High', '1038.HK')":49.8164599843,
    "('Low', '1038.HK')":49.1034381542,
    "('Open', '1038.HK')":49.6263201043,
    "('Volume', '1038.HK')":1436469
  },
  {
    "('Date', '')":"2025-02-10",
    "('Close', '1038.HK')":48.9608345032,
    "('High', '1038.HK')":49.4837164764,
    "('Low', '1038.HK')":48.8182286802,
    "('Open', '1038.HK')":49.436182411,
    "('Volume', '1038.HK')":2229381
  },
  {
    "('Date', '')":"2025-02-11",
    "('Close', '1038.HK')":48.8657646179,
    "('High', '1038.HK')":49.2935748183,
    "('Low', '1038.HK')":48.6280906726,
    "('Open', '1038.HK')":48.9608327454,
    "('Volume', '1038.HK')":3099901
  },
  {
    "('Date', '')":"2025-02-12",
    "('Close', '1038.HK')":48.8657646179,
    "('High', '1038.HK')":49.1985066908,
    "('Low', '1038.HK')":48.7706928638,
    "('Open', '1038.HK')":48.8657646179,
    "('Volume', '1038.HK')":2349709
  },
  {
    "('Date', '')":"2025-02-13",
    "('Close', '1038.HK')":48.8182258606,
    "('High', '1038.HK')":49.1034374901,
    "('Low', '1038.HK')":48.6280896098,
    "('Open', '1038.HK')":48.9132976126,
    "('Volume', '1038.HK')":3005930
  },
  {
    "('Date', '')":"2025-02-14",
    "('Close', '1038.HK')":48.4854850769,
    "('High', '1038.HK')":49.1985069163,
    "('Low', '1038.HK')":48.2953451944,
    "('Open', '1038.HK')":49.1034387883,
    "('Volume', '1038.HK')":3230618
  },
  {
    "('Date', '')":"2025-02-17",
    "('Close', '1038.HK')":49.3886489868,
    "('High', '1038.HK')":49.4361830529,
    "('Low', '1038.HK')":48.1052074431,
    "('Open', '1038.HK')":48.4854872249,
    "('Volume', '1038.HK')":2805176
  },
  {
    "('Date', '')":"2025-02-18",
    "('Close', '1038.HK')":49.1509742737,
    "('High', '1038.HK')":49.388648227,
    "('Low', '1038.HK')":48.6280923017,
    "('Open', '1038.HK')":49.388648227,
    "('Volume', '1038.HK')":2317408
  },
  {
    "('Date', '')":"2025-02-19",
    "('Close', '1038.HK')":49.2935752869,
    "('High', '1038.HK')":49.3411129777,
    "('Low', '1038.HK')":48.6280911348,
    "('Open', '1038.HK')":48.675625199,
    "('Volume', '1038.HK')":2420644
  },
  {
    "('Date', '')":"2025-02-20",
    "('Close', '1038.HK')":49.5787849426,
    "('High', '1038.HK')":49.9590610677,
    "('Low', '1038.HK')":48.9608312529,
    "('Open', '1038.HK')":49.2935733156,
    "('Volume', '1038.HK')":3269065
  },
  {
    "('Date', '')":"2025-02-21",
    "('Close', '1038.HK')":49.6263237,
    "('High', '1038.HK')":49.8639976606,
    "('Low', '1038.HK')":49.3411156725,
    "('Open', '1038.HK')":49.7213918335,
    "('Volume', '1038.HK')":2312812
  },
  {
    "('Date', '')":"2025-02-24",
    "('Close', '1038.HK')":50.5294799805,
    "('High', '1038.HK')":51.1474300349,
    "('Low', '1038.HK')":49.0558986837,
    "('Open', '1038.HK')":49.2460385568,
    "('Volume', '1038.HK')":3103071
  },
  {
    "('Date', '')":"2025-02-25",
    "('Close', '1038.HK')":50.5770187378,
    "('High', '1038.HK')":51.0523666514,
    "('Low', '1038.HK')":50.1016708241,
    "('Open', '1038.HK')":50.5770187378,
    "('Volume', '1038.HK')":2709952
  },
  {
    "('Date', '')":"2025-02-26",
    "('Close', '1038.HK')":50.7671546936,
    "('High', '1038.HK')":51.5752446335,
    "('Low', '1038.HK')":50.6720829423,
    "('Open', '1038.HK')":50.8622228183,
    "('Volume', '1038.HK')":2494712
  },
  {
    "('Date', '')":"2025-02-27",
    "('Close', '1038.HK')":50.9572944641,
    "('High', '1038.HK')":51.2425061112,
    "('Low', '1038.HK')":50.0541363371,
    "('Open', '1038.HK')":50.7671582015,
    "('Volume', '1038.HK')":2188022
  },
  {
    "('Date', '')":"2025-02-28",
    "('Close', '1038.HK')":50.719619751,
    "('High', '1038.HK')":51.0523654587,
    "('Low', '1038.HK')":49.9590638322,
    "('Open', '1038.HK')":50.719619751,
    "('Volume', '1038.HK')":2900183
  },
  {
    "('Date', '')":"2025-03-03",
    "('Close', '1038.HK')":49.7213859558,
    "('High', '1038.HK')":50.9572896795,
    "('Low', '1038.HK')":49.4837120233,
    "('Open', '1038.HK')":50.719615747,
    "('Volume', '1038.HK')":2198016
  },
  {
    "('Date', '')":"2025-03-04",
    "('Close', '1038.HK')":50.1967353821,
    "('High', '1038.HK')":50.291807134,
    "('Low', '1038.HK')":49.4361794997,
    "('Open', '1038.HK')":49.6738534396,
    "('Volume', '1038.HK')":2043915
  },
  {
    "('Date', '')":"2025-03-05",
    "('Close', '1038.HK')":51.2900390625,
    "('High', '1038.HK')":51.9555268469,
    "('Low', '1038.HK')":50.3868773285,
    "('Open', '1038.HK')":50.3868773285,
    "('Volume', '1038.HK')":3526978
  },
  {
    "('Date', '')":"2025-03-06",
    "('Close', '1038.HK')":51.4326400757,
    "('High', '1038.HK')":51.5277118293,
    "('Low', '1038.HK')":51.0048298774,
    "('Open', '1038.HK')":51.147432068,
    "('Volume', '1038.HK')":2213748
  },
  {
    "('Date', '')":"2025-03-07",
    "('Close', '1038.HK')":52.0981254578,
    "('High', '1038.HK')":52.3357993911,
    "('Low', '1038.HK')":51.4326377192,
    "('Open', '1038.HK')":51.4326377192,
    "('Volume', '1038.HK')":2718406
  },
  {
    "('Date', '')":"2025-03-10",
    "('Close', '1038.HK')":51.9555244446,
    "('High', '1038.HK')":52.1456606942,
    "('Low', '1038.HK')":51.4326388782,
    "('Open', '1038.HK')":52.0981266318,
    "('Volume', '1038.HK')":1628351
  },
  {
    "('Date', '')":"2025-03-11",
    "('Close', '1038.HK')":51.6227798462,
    "('High', '1038.HK')":52.2407335505,
    "('Low', '1038.HK')":51.5752457828,
    "('Open', '1038.HK')":51.9079878533,
    "('Volume', '1038.HK')":1549948
  },
  {
    "('Date', '')":"2025-03-12",
    "('Close', '1038.HK')":52.1931991577,
    "('High', '1038.HK')":52.2407332208,
    "('Low', '1038.HK')":50.8146895676,
    "('Open', '1038.HK')":51.6227795205,
    "('Volume', '1038.HK')":1640168
  },
  {
    "('Date', '')":"2025-03-13",
    "('Close', '1038.HK')":51.8604507446,
    "('High', '1038.HK')":52.6685442817,
    "('Low', '1038.HK')":51.6703108755,
    "('Open', '1038.HK')":52.0030565531,
    "('Volume', '1038.HK')":1331816
  },
  {
    "('Date', '')":"2025-03-14",
    "('Close', '1038.HK')":50.3393440247,
    "('High', '1038.HK')":52.1456638934,
    "('Low', '1038.HK')":50.1967382021,
    "('Open', '1038.HK')":51.8129218095,
    "('Volume', '1038.HK')":3541326
  },
  {
    "('Date', '')":"2025-03-17",
    "('Close', '1038.HK')":50.3393440247,
    "('High', '1038.HK')":51.0998999497,
    "('Low', '1038.HK')":50.0065983141,
    "('Open', '1038.HK')":50.1016700714,
    "('Volume', '1038.HK')":2099104
  },
  {
    "('Date', '')":"2025-03-18",
    "('Close', '1038.HK')":48.8657646179,
    "('High', '1038.HK')":50.4344104814,
    "('Low', '1038.HK')":48.2478109093,
    "('Open', '1038.HK')":50.3868764176,
    "('Volume', '1038.HK')":7300185
  },
  {
    "('Date', '')":"2025-03-19",
    "('Close', '1038.HK')":48.2002792358,
    "('High', '1038.HK')":49.3886490216,
    "('Low', '1038.HK')":47.5823254966,
    "('Open', '1038.HK')":48.8657670412,
    "('Volume', '1038.HK')":6532179
  },
  {
    "('Date', '')":"2025-03-20",
    "('Close', '1038.HK')":45.4432563782,
    "('High', '1038.HK')":47.772461704,
    "('Low', '1038.HK')":45.3006541908,
    "('Open', '1038.HK')":47.62985589,
    "('Volume', '1038.HK')":11848244
  },
  {
    "('Date', '')":"2025-03-21",
    "('Close', '1038.HK')":45.7284660339,
    "('High', '1038.HK')":46.2038139288,
    "('Low', '1038.HK')":45.4907920865,
    "('Open', '1038.HK')":45.6333979056,
    "('Volume', '1038.HK')":5435882
  },
  {
    "('Date', '')":"2025-03-24",
    "('Close', '1038.HK')":45.0154457092,
    "('High', '1038.HK')":45.8235393337,
    "('Low', '1038.HK')":44.8728435119,
    "('Open', '1038.HK')":45.633399444,
    "('Volume', '1038.HK')":3536499
  },
  {
    "('Date', '')":"2025-03-25",
    "('Close', '1038.HK')":44.7302360535,
    "('High', '1038.HK')":45.253118011,
    "('Low', '1038.HK')":44.7302360535,
    "('Open', '1038.HK')":45.0154440642,
    "('Volume', '1038.HK')":2081609
  },
  {
    "('Date', '')":"2025-03-26",
    "('Close', '1038.HK')":45.1105155945,
    "('High', '1038.HK')":45.728465677,
    "('Low', '1038.HK')":44.7777698947,
    "('Open', '1038.HK')":45.4432576676,
    "('Volume', '1038.HK')":2108430
  },
  {
    "('Date', '')":"2025-03-27",
    "('Close', '1038.HK')":44.4450263977,
    "('High', '1038.HK')":45.4907902741,
    "('Low', '1038.HK')":44.3974923354,
    "('Open', '1038.HK')":45.1105141493,
    "('Volume', '1038.HK')":2985507
  },
  {
    "('Date', '')":"2025-03-28",
    "('Close', '1038.HK')":44.6827011108,
    "('High', '1038.HK')":45.0629808688,
    "('Low', '1038.HK')":44.3024213529,
    "('Open', '1038.HK')":44.8253069267,
    "('Volume', '1038.HK')":1596550
  },
  {
    "('Date', '')":"2025-03-31",
    "('Close', '1038.HK')":44.3024215698,
    "('High', '1038.HK')":45.1105151528,
    "('Low', '1038.HK')":44.2548875065,
    "('Open', '1038.HK')":44.587633203,
    "('Volume', '1038.HK')":2665661
  },
  {
    "('Date', '')":"2025-04-01",
    "('Close', '1038.HK')":45.0154457092,
    "('High', '1038.HK')":45.5858653782,
    "('Low', '1038.HK')":44.6827036223,
    "('Open', '1038.HK')":44.6827036223,
    "('Volume', '1038.HK')":2613887
  },
  {
    "('Date', '')":"2025-04-02",
    "('Close', '1038.HK')":45.300655365,
    "('High', '1038.HK')":45.4907916197,
    "('Low', '1038.HK')":44.58763353,
    "('Open', '1038.HK')":44.9203756024,
    "('Volume', '1038.HK')":2361710
  },
  {
    "('Date', '')":"2025-04-03",
    "('Close', '1038.HK')":45.7284660339,
    "('High', '1038.HK')":45.7760037247,
    "('Low', '1038.HK')":44.3974941043,
    "('Open', '1038.HK')":44.6827021159,
    "('Volume', '1038.HK')":3283104
  },
  {
    "('Date', '')":"2025-04-07",
    "('Close', '1038.HK')":44.9679069519,
    "('High', '1038.HK')":46.5365563448,
    "('Low', '1038.HK')":43.9221431077,
    "('Open', '1038.HK')":44.7777670821,
    "('Volume', '1038.HK')":10798468
  },
  {
    "('Date', '')":"2025-04-08",
    "('Close', '1038.HK')":44.0647468567,
    "('High', '1038.HK')":45.8710702444,
    "('Low', '1038.HK')":43.541864916,
    "('Open', '1038.HK')":44.4925606724,
    "('Volume', '1038.HK')":4973333
  },
  {
    "('Date', '')":"2025-04-09",
    "('Close', '1038.HK')":44.540096283,
    "('High', '1038.HK')":44.6351680379,
    "('Low', '1038.HK')":43.0189844706,
    "('Open', '1038.HK')":43.0189844706,
    "('Volume', '1038.HK')":3266937
  },
  {
    "('Date', '')":"2025-04-10",
    "('Close', '1038.HK')":45.1105155945,
    "('High', '1038.HK')":46.1087454406,
    "('Low', '1038.HK')":43.9221458666,
    "('Open', '1038.HK')":45.0154438403,
    "('Volume', '1038.HK')":8988922
  },
  {
    "('Date', '')":"2025-04-11",
    "('Close', '1038.HK')":45.7284660339,
    "('High', '1038.HK')":45.871071853,
    "('Low', '1038.HK')":44.9203760633,
    "('Open', '1038.HK')":45.348189894,
    "('Volume', '1038.HK')":2346502
  },
  {
    "('Date', '')":"2025-04-14",
    "('Close', '1038.HK')":45.7760009766,
    "('High', '1038.HK')":46.2988829042,
    "('Low', '1038.HK')":45.6809292273,
    "('Open', '1038.HK')":46.061208971,
    "('Volume', '1038.HK')":2486644
  },
  {
    "('Date', '')":"2025-04-15",
    "('Close', '1038.HK')":45.5383300781,
    "('High', '1038.HK')":46.1087461051,
    "('Low', '1038.HK')":45.253118438,
    "('Open', '1038.HK')":45.8235380916,
    "('Volume', '1038.HK')":2673137
  },
  {
    "('Date', '')":"2025-04-16",
    "('Close', '1038.HK')":45.5858650208,
    "('High', '1038.HK')":45.8235389743,
    "('Low', '1038.HK')":45.0154453562,
    "('Open', '1038.HK')":45.2531193098,
    "('Volume', '1038.HK')":3579605
  },
  {
    "('Date', '')":"2025-04-17",
    "('Close', '1038.HK')":46.8693008423,
    "('High', '1038.HK')":47.059440722,
    "('Low', '1038.HK')":45.5858630005,
    "('Open', '1038.HK')":45.5858630005,
    "('Volume', '1038.HK')":2419332
  },
  {
    "('Date', '')":"2025-04-22",
    "('Close', '1038.HK')":47.3921852112,
    "('High', '1038.HK')":47.4872569692,
    "('Low', '1038.HK')":46.6316292799,
    "('Open', '1038.HK')":47.154511256,
    "('Volume', '1038.HK')":3073979
  },
  {
    "('Date', '')":"2025-04-23",
    "('Close', '1038.HK')":48.2478103638,
    "('High', '1038.HK')":48.39041618,
    "('Low', '1038.HK')":47.3446486563,
    "('Open', '1038.HK')":47.3446486563,
    "('Volume', '1038.HK')":3512992
  },
  {
    "('Date', '')":"2025-04-24",
    "('Close', '1038.HK')":48.2002792358,
    "('High', '1038.HK')":48.5330213252,
    "('Low', '1038.HK')":47.6298595627,
    "('Open', '1038.HK')":47.6298595627,
    "('Volume', '1038.HK')":2233091
  },
  {
    "('Date', '')":"2025-04-25",
    "('Close', '1038.HK')":49.1985054016,
    "('High', '1038.HK')":49.6263192174,
    "('Low', '1038.HK')":48.1052038309,
    "('Open', '1038.HK')":48.1052038309,
    "('Volume', '1038.HK')":3773290
  },
  {
    "('Date', '')":"2025-04-28",
    "('Close', '1038.HK')":49.1985054016,
    "('High', '1038.HK')":49.7213873424,
    "('Low', '1038.HK')":49.1509713391,
    "('Open', '1038.HK')":49.2460394641,
    "('Volume', '1038.HK')":2303375
  },
  {
    "('Date', '')":"2025-04-29",
    "('Close', '1038.HK')":49.1985054016,
    "('High', '1038.HK')":50.1967352207,
    "('Low', '1038.HK')":49.0558995875,
    "('Open', '1038.HK')":49.1985054016,
    "('Volume', '1038.HK')":1890549
  },
  {
    "('Date', '')":"2025-04-30",
    "('Close', '1038.HK')":49.7213859558,
    "('High', '1038.HK')":49.9115258271,
    "('Low', '1038.HK')":49.0558982195,
    "('Open', '1038.HK')":49.1985040296,
    "('Volume', '1038.HK')":2623647
  },
  {
    "('Date', '')":"2025-05-02",
    "('Close', '1038.HK')":49.4361801147,
    "('High', '1038.HK')":49.9590620637,
    "('Low', '1038.HK')":48.9132981658,
    "('Open', '1038.HK')":49.5312482412,
    "('Volume', '1038.HK')":1548393
  },
  {
    "('Date', '')":"2025-05-06",
    "('Close', '1038.HK')":49.9590606689,
    "('High', '1038.HK')":49.9590606689,
    "('Low', '1038.HK')":49.4361787346,
    "('Open', '1038.HK')":49.4837127965,
    "('Volume', '1038.HK')":1946633
  },
  {
    "('Date', '')":"2025-05-07",
    "('Close', '1038.HK')":49.9590606689,
    "('High', '1038.HK')":50.2442686671,
    "('Low', '1038.HK')":49.6263186089,
    "('Open', '1038.HK')":50.1967346052,
    "('Volume', '1038.HK')":1518803
  },
  {
    "('Date', '')":"2025-05-08",
    "('Close', '1038.HK')":50.3868751526,
    "('High', '1038.HK')":50.4819432777,
    "('Low', '1038.HK')":49.5787852093,
    "('Open', '1038.HK')":50.2918070275,
    "('Volume', '1038.HK')":1503502
  },
  {
    "('Date', '')":"2025-05-09",
    "('Close', '1038.HK')":50.2442703247,
    "('High', '1038.HK')":50.5294819589,
    "('Low', '1038.HK')":50.0541340707,
    "('Open', '1038.HK')":50.5294819589,
    "('Volume', '1038.HK')":511041
  },
  {
    "('Date', '')":"2025-05-12",
    "('Close', '1038.HK')":50.6245498657,
    "('High', '1038.HK')":51.1949658784,
    "('Low', '1038.HK')":50.2442701062,
    "('Open', '1038.HK')":50.2442701062,
    "('Volume', '1038.HK')":1738275
  },
  {
    "('Date', '')":"2025-05-13",
    "('Close', '1038.HK')":49.4361801147,
    "('High', '1038.HK')":50.624549829,
    "('Low', '1038.HK')":49.1509721086,
    "('Open', '1038.HK')":50.624549829,
    "('Volume', '1038.HK')":1664755
  },
  {
    "('Date', '')":"2025-05-14",
    "('Close', '1038.HK')":49.6738548279,
    "('High', '1038.HK')":49.8639947104,
    "('Low', '1038.HK')":49.2460409988,
    "('Open', '1038.HK')":49.8639947104,
    "('Volume', '1038.HK')":942227
  },
  {
    "('Date', '')":"2025-05-15",
    "('Close', '1038.HK')":49.3886489868,
    "('High', '1038.HK')":49.6738570099,
    "('Low', '1038.HK')":48.9608351389,
    "('Open', '1038.HK')":49.6738570099,
    "('Volume', '1038.HK')":775679
  },
  {
    "('Date', '')":"2025-05-16",
    "('Close', '1038.HK')":49.2460403442,
    "('High', '1038.HK')":49.3886461609,
    "('Low', '1038.HK')":49.0083664009,
    "('Open', '1038.HK')":49.3886461609,
    "('Volume', '1038.HK')":1307783
  },
  {
    "('Date', '')":"2025-05-19",
    "('Close', '1038.HK')":49.53125,
    "('High', '1038.HK')":49.6263217565,
    "('Low', '1038.HK')":49.0083680325,
    "('Open', '1038.HK')":49.0559020974,
    "('Volume', '1038.HK')":1082466
  },
  {
    "('Date', '')":"2025-05-20",
    "('Close', '1038.HK')":49.7689247131,
    "('High', '1038.HK')":50.0065986681,
    "('Low', '1038.HK')":49.5312507582,
    "('Open', '1038.HK')":49.7689247131,
    "('Volume', '1038.HK')":1455565
  },
  {
    "('Date', '')":"2025-05-21",
    "('Close', '1038.HK')":49.5787849426,
    "('High', '1038.HK')":49.863992943,
    "('Low', '1038.HK')":49.5312472537,
    "('Open', '1038.HK')":49.7689211918,
    "('Volume', '1038.HK')":1182098
  },
  {
    "('Date', '')":"2025-05-22",
    "('Close', '1038.HK')":49.6263237,
    "('High', '1038.HK')":49.8639976606,
    "('Low', '1038.HK')":49.3886497393,
    "('Open', '1038.HK')":49.5787896332,
    "('Volume', '1038.HK')":1285521
  },
  {
    "('Date', '')":"2025-05-23",
    "('Close', '1038.HK')":49.2935752869,
    "('High', '1038.HK')":49.5312492345,
    "('Low', '1038.HK')":49.1985071585,
    "('Open', '1038.HK')":49.5312492345,
    "('Volume', '1038.HK')":2016413
  },
  {
    "('Date', '')":"2025-05-26",
    "('Close', '1038.HK')":49.8950767517,
    "('High', '1038.HK')":50.190900383,
    "('Low', '1038.HK')":49.2541343275,
    "('Open', '1038.HK')":49.5006515125,
    "('Volume', '1038.HK')":1729099
  },
  {
    "('Date', '')":"2025-05-27",
    "('Close', '1038.HK')":49.1062202454,
    "('High', '1038.HK')":50.2895034314,
    "('Low', '1038.HK')":49.1062202454,
    "('Open', '1038.HK')":49.9443808928,
    "('Volume', '1038.HK')":1149091
  },
  {
    "('Date', '')":"2025-05-28",
    "('Close', '1038.HK')":49.2541351318,
    "('High', '1038.HK')":49.3034378173,
    "('Low', '1038.HK')":48.5638862501,
    "('Open', '1038.HK')":49.1062233138,
    "('Volume', '1038.HK')":2165780
  },
  {
    "('Date', '')":"2025-05-29",
    "('Close', '1038.HK')":49.0076179504,
    "('High', '1038.HK')":49.155526007,
    "('Low', '1038.HK')":48.6624916287,
    "('Open', '1038.HK')":49.056920636,
    "('Volume', '1038.HK')":1284049
  },
  {
    "('Date', '')":"2025-05-30",
    "('Close', '1038.HK')":50.0429878235,
    "('High', '1038.HK')":50.0429878235,
    "('Low', '1038.HK')":48.8104019165,
    "('Open', '1038.HK')":48.8104019165,
    "('Volume', '1038.HK')":5270436
  },
  {
    "('Date', '')":"2025-06-02",
    "('Close', '1038.HK')":49.9443817139,
    "('High', '1038.HK')":50.0429870803,
    "('Low', '1038.HK')":49.3527382304,
    "('Open', '1038.HK')":49.5992554081,
    "('Volume', '1038.HK')":2085664
  },
  {
    "('Date', '')":"2025-06-03",
    "('Close', '1038.HK')":51.0290565491,
    "('High', '1038.HK')":51.6700027253,
    "('Low', '1038.HK')":49.9936851395,
    "('Open', '1038.HK')":49.9936851395,
    "('Volume', '1038.HK')":3774122
  },
  {
    "('Date', '')":"2025-06-04",
    "('Close', '1038.HK')":50.5360221863,
    "('High', '1038.HK')":51.078359233,
    "('Low', '1038.HK')":50.0922905075,
    "('Open', '1038.HK')":50.9797538651,
    "('Volume', '1038.HK')":2557288
  },
  {
    "('Date', '')":"2025-06-05",
    "('Close', '1038.HK')":51.5713920593,
    "('High', '1038.HK')":51.6206947418,
    "('Low', '1038.HK')":50.6839324897,
    "('Open', '1038.HK')":50.7825378547,
    "('Volume', '1038.HK')":3075264
  },
  {
    "('Date', '')":"2025-06-06",
    "('Close', '1038.HK')":51.3248748779,
    "('High', '1038.HK')":51.719303861,
    "('Low', '1038.HK')":51.3248748779,
    "('Open', '1038.HK')":51.6206947344,
    "('Volume', '1038.HK')":1802637
  },
  {
    "('Date', '')":"2025-06-09",
    "('Close', '1038.HK')":51.1769676208,
    "('High', '1038.HK')":51.4234847987,
    "('Low', '1038.HK')":50.9797531263,
    "('Open', '1038.HK')":51.3741783539,
    "('Volume', '1038.HK')":1530067
  },
  {
    "('Date', '')":"2025-06-10",
    "('Close', '1038.HK')":50.9797554016,
    "('High', '1038.HK')":51.3248779613,
    "('Low', '1038.HK')":50.9304527162,
    "('Open', '1038.HK')":51.2755752759,
    "('Volume', '1038.HK')":1205850
  },
  {
    "('Date', '')":"2025-06-11",
    "('Close', '1038.HK')":50.6839332581,
    "('High', '1038.HK')":51.1769676136,
    "('Low', '1038.HK')":50.6839332581,
    "('Open', '1038.HK')":51.1276611688,
    "('Volume', '1038.HK')":1439600
  },
  {
    "('Date', '')":"2025-06-12",
    "('Close', '1038.HK')":51.0783576965,
    "('High', '1038.HK')":51.1769668231,
    "('Low', '1038.HK')":50.6346260311,
    "('Open', '1038.HK')":50.6346260311,
    "('Volume', '1038.HK')":1097549
  },
  {
    "('Date', '')":"2025-06-13",
    "('Close', '1038.HK')":50.7825393677,
    "('High', '1038.HK')":51.3248764144,
    "('Low', '1038.HK')":50.7332366837,
    "('Open', '1038.HK')":51.1769683625,
    "('Volume', '1038.HK')":1543929
  },
  {
    "('Date', '')":"2025-06-16",
    "('Close', '1038.HK')":51.7193069458,
    "('High', '1038.HK')":51.7686096312,
    "('Low', '1038.HK')":50.7825408764,
    "('Open', '1038.HK')":50.7825408764,
    "('Volume', '1038.HK')":2062537
  },
  {
    "('Date', '')":"2025-06-17",
    "('Close', '1038.HK')":51.7686080933,
    "('High', '1038.HK')":51.9658225907,
    "('Low', '1038.HK')":51.1769683625,
    "('Open', '1038.HK')":51.7193054093,
    "('Volume', '1038.HK')":1148174
  },
  {
    "('Date', '')":"2025-06-18",
    "('Close', '1038.HK')":51.5713920593,
    "('High', '1038.HK')":52.163035534,
    "('Low', '1038.HK')":51.5220893768,
    "('Open', '1038.HK')":51.8179092334,
    "('Volume', '1038.HK')":1397071
  },
  {
    "('Date', '')":"2025-06-19",
    "('Close', '1038.HK')":50.9304504395,
    "('High', '1038.HK')":51.5713928448,
    "('Low', '1038.HK')":50.7825386281,
    "('Open', '1038.HK')":51.5713928448,
    "('Volume', '1038.HK')":702233
  },
  {
    "('Date', '')":"2025-06-20",
    "('Close', '1038.HK')":51.0783576965,
    "('High', '1038.HK')":51.5713920445,
    "('Low', '1038.HK')":50.7825378401,
    "('Open', '1038.HK')":50.9304496491,
    "('Volume', '1038.HK')":2233091
  },
  {
    "('Date', '')":"2025-06-23",
    "('Close', '1038.HK')":50.9304504395,
    "('High', '1038.HK')":51.4234847951,
    "('Low', '1038.HK')":50.7825386281,
    "('Open', '1038.HK')":51.0783584892,
    "('Volume', '1038.HK')":1196301
  },
  {
    "('Date', '')":"2025-06-24",
    "('Close', '1038.HK')":51.5713920593,
    "('High', '1038.HK')":51.8179092334,
    "('Low', '1038.HK')":50.8811432197,
    "('Open', '1038.HK')":50.8811432197,
    "('Volume', '1038.HK')":1500481
  },
  {
    "('Date', '')":"2025-06-25",
    "('Close', '1038.HK')":52.6067657471,
    "('High', '1038.HK')":52.7546775626,
    "('Low', '1038.HK')":51.9658233233,
    "('Open', '1038.HK')":52.0644286927,
    "('Volume', '1038.HK')":2071490
  },
  {
    "('Date', '')":"2025-06-26",
    "('Close', '1038.HK')":52.2123413086,
    "('High', '1038.HK')":52.8039810567,
    "('Low', '1038.HK')":52.1137321762,
    "('Open', '1038.HK')":52.6067665535,
    "('Volume', '1038.HK')":1994751
  },
  {
    "('Date', '')":"2025-06-27",
    "('Close', '1038.HK')":51.4234848022,
    "('High', '1038.HK')":52.754676058,
    "('Low', '1038.HK')":51.2262703077,
    "('Open', '1038.HK')":52.754676058,
    "('Volume', '1038.HK')":1657825
  },
  {
    "('Date', '')":"2025-06-30",
    "('Close', '1038.HK')":51.226272583,
    "('High', '1038.HK')":51.5713951427,
    "('Low', '1038.HK')":50.8318435763,
    "('Open', '1038.HK')":51.2755752685,
    "('Volume', '1038.HK')":1992461
  },
  {
    "('Date', '')":"2025-07-02",
    "('Close', '1038.HK')":51.4234848022,
    "('High', '1038.HK')":52.212339019,
    "('Low', '1038.HK')":51.2755729909,
    "('Open', '1038.HK')":51.3741783574,
    "('Volume', '1038.HK')":2552305
  },
  {
    "('Date', '')":"2025-07-03",
    "('Close', '1038.HK')":51.916519165,
    "('High', '1038.HK')":52.1630363429,
    "('Low', '1038.HK')":51.4727874926,
    "('Open', '1038.HK')":51.8672127202,
    "('Volume', '1038.HK')":1398957
  },
  {
    "('Date', '')":"2025-07-04",
    "('Close', '1038.HK')":52.2123413086,
    "('High', '1038.HK')":52.261643994,
    "('Low', '1038.HK')":51.4234870572,
    "('Open', '1038.HK')":52.261643994,
    "('Volume', '1038.HK')":769801
  },
  {
    "('Date', '')":"2025-07-07",
    "('Close', '1038.HK')":51.5220909119,
    "('High', '1038.HK')":52.2616424561,
    "('Low', '1038.HK')":51.1769683625,
    "('Open', '1038.HK')":52.1630370881,
    "('Volume', '1038.HK')":1241411
  },
  {
    "('Date', '')":"2025-07-08",
    "('Close', '1038.HK')":51.226272583,
    "('High', '1038.HK')":51.6700042751,
    "('Low', '1038.HK')":50.9797553942,
    "('Open', '1038.HK')":51.5220924572,
    "('Volume', '1038.HK')":1162360
  },
  {
    "('Date', '')":"2025-07-09",
    "('Close', '1038.HK')":50.6346282959,
    "('High', '1038.HK')":51.2755744815,
    "('Low', '1038.HK')":50.4374175571,
    "('Open', '1038.HK')":51.2755744815,
    "('Volume', '1038.HK')":1601603
  },
  {
    "('Date', '')":"2025-07-10",
    "('Close', '1038.HK')":50.3388061523,
    "('High', '1038.HK')":50.8811431826,
    "('Low', '1038.HK')":50.2895034699,
    "('Open', '1038.HK')":50.6346260087,
    "('Volume', '1038.HK')":1112511
  },
  {
    "('Date', '')":"2025-07-11",
    "('Close', '1038.HK')":50.4374160767,
    "('High', '1038.HK')":50.7332359377,
    "('Low', '1038.HK')":50.2895042654,
    "('Open', '1038.HK')":50.6346268096,
    "('Volume', '1038.HK')":2234670
  },
  {
    "('Date', '')":"2025-07-14",
    "('Close', '1038.HK')":50.4374160767,
    "('High', '1038.HK')":50.5853241264,
    "('Low', '1038.HK')":50.0922897708,
    "('Open', '1038.HK')":50.3881096319,
    "('Volume', '1038.HK')":1167219
  },
  {
    "('Date', '')":"2025-07-15",
    "('Close', '1038.HK')":51.1276626587,
    "('High', '1038.HK')":51.2262717896,
    "('Low', '1038.HK')":50.6346282887,
    "('Open', '1038.HK')":50.7332374197,
    "('Volume', '1038.HK')":1936447
  },
  {
    "('Date', '')":"2025-07-16",
    "('Close', '1038.HK')":51.7686080933,
    "('High', '1038.HK')":51.8672134612,
    "('Low', '1038.HK')":50.8318420516,
    "('Open', '1038.HK')":50.8318420516,
    "('Volume', '1038.HK')":2096844
  },
  {
    "('Date', '')":"2025-07-17",
    "('Close', '1038.HK')":52.1137313843,
    "('High', '1038.HK')":52.2123405152,
    "('Low', '1038.HK')":51.6206970145,
    "('Open', '1038.HK')":51.76860883,
    "('Volume', '1038.HK')":1420197
  },
  {
    "('Date', '')":"2025-07-18",
    "('Close', '1038.HK')":51.6700019836,
    "('High', '1038.HK')":52.4588562005,
    "('Low', '1038.HK')":51.472787489,
    "('Open', '1038.HK')":52.3109443891,
    "('Volume', '1038.HK')":1608744
  },
  {
    "('Date', '')":"2025-07-21",
    "('Close', '1038.HK')":51.8179092407,
    "('High', '1038.HK')":51.9165183673,
    "('Low', '1038.HK')":51.4234840191,
    "('Open', '1038.HK')":51.5220893841,
    "('Volume', '1038.HK')":814577
  },
  {
    "('Date', '')":"2025-07-22",
    "('Close', '1038.HK')":52.2616424561,
    "('High', '1038.HK')":52.2616424561,
    "('Low', '1038.HK')":51.8179107772,
    "('Open', '1038.HK')":51.8179107772,
    "('Volume', '1038.HK')":1600373
  },
  {
    "('Date', '')":"2025-07-23",
    "('Close', '1038.HK')":52.6560707092,
    "('High', '1038.HK')":52.7546760758,
    "('Low', '1038.HK')":52.1137299086,
    "('Open', '1038.HK')":52.4095535313,
    "('Volume', '1038.HK')":1623053
  },
  {
    "('Date', '')":"2025-07-24",
    "('Close', '1038.HK')":52.8039779663,
    "('High', '1038.HK')":52.9025870929,
    "('Low', '1038.HK')":52.5081581096,
    "('Open', '1038.HK')":52.7546752838,
    "('Volume', '1038.HK')":1407246
  },
  {
    "('Date', '')":"2025-07-25",
    "('Close', '1038.HK')":53.0998001099,
    "('High', '1038.HK')":53.9379607953,
    "('Low', '1038.HK')":52.5574630555,
    "('Open', '1038.HK')":52.5574630555,
    "('Volume', '1038.HK')":1985468
  },
  {
    "('Date', '')":"2025-07-28",
    "('Close', '1038.HK')":54.72681427,
    "('High', '1038.HK')":55.2198486328,
    "('Low', '1038.HK')":53.0997993682,
    "('Open', '1038.HK')":53.0997993682,
    "('Volume', '1038.HK')":3442695
  },
  {
    "('Date', '')":"2025-07-29",
    "('Close', '1038.HK')":55.1705474854,
    "('High', '1038.HK')":55.2198501707,
    "('Low', '1038.HK')":54.0858696001,
    "('Open', '1038.HK')":55.0226356678,
    "('Volume', '1038.HK')":2334815
  },
  {
    "('Date', '')":"2025-07-30",
    "('Close', '1038.HK')":54.4309959412,
    "('High', '1038.HK')":55.1212448209,
    "('Low', '1038.HK')":54.1844787528,
    "('Open', '1038.HK')":55.1212448209,
    "('Volume', '1038.HK')":1717064
  },
  {
    "('Date', '')":"2025-07-31",
    "('Close', '1038.HK')":54.5789031982,
    "('High', '1038.HK')":55.1705466986,
    "('Low', '1038.HK')":54.3323860135,
    "('Open', '1038.HK')":54.3323860135,
    "('Volume', '1038.HK')":2582883
  },
  {
    "('Date', '')":"2025-08-01",
    "('Close', '1038.HK')":53.7407455444,
    "('High', '1038.HK')":54.825419638,
    "('Low', '1038.HK')":53.592833731,
    "('Open', '1038.HK')":54.5789024566,
    "('Volume', '1038.HK')":1537305
  },
  {
    "('Date', '')":"2025-08-04",
    "('Close', '1038.HK')":54.0365638733,
    "('High', '1038.HK')":54.3816901744,
    "('Low', '1038.HK')":53.5435295245,
    "('Open', '1038.HK')":53.5435295245,
    "('Volume', '1038.HK')":1114103
  },
  {
    "('Date', '')":"2025-08-05",
    "('Close', '1038.HK')":54.1844787598,
    "('High', '1038.HK')":54.3816932628,
    "('Low', '1038.HK')":53.6421416976,
    "('Open', '1038.HK')":53.6421416976,
    "('Volume', '1038.HK')":1510299
  },
  {
    "('Date', '')":"2025-08-06",
    "('Close', '1038.HK')":53.7407455444,
    "('High', '1038.HK')":54.2337799072,
    "('Low', '1038.HK')":53.3463165496,
    "('Open', '1038.HK')":54.1844772233,
    "('Volume', '1038.HK')":1057572
  },
  {
    "('Date', '')":"2025-08-07",
    "('Close', '1038.HK')":54.2830810547,
    "('High', '1038.HK')":54.4802955465,
    "('Low', '1038.HK')":53.5435295314,
    "('Open', '1038.HK')":53.5435295314,
    "('Volume', '1038.HK')":941393
  },
  {
    "('Date', '')":"2025-08-08",
    "('Close', '1038.HK')":54.72681427,
    "('High', '1038.HK')":54.9733314514,
    "('Low', '1038.HK')":54.1351745393,
    "('Open', '1038.HK')":54.4309944047,
    "('Volume', '1038.HK')":1177431
  },
  {
    "('Date', '')":"2025-08-11",
    "('Close', '1038.HK')":55.2198486328,
    "('High', '1038.HK')":55.3184540007,
    "('Low', '1038.HK')":54.72681427,
    "('Open', '1038.HK')":54.825419638,
    "('Volume', '1038.HK')":926967
  },
  {
    "('Date', '')":"2025-08-12",
    "('Close', '1038.HK')":54.4802970886,
    "('High', '1038.HK')":55.3184540007,
    "('Low', '1038.HK')":54.4309944047,
    "('Open', '1038.HK')":55.3184540007,
    "('Volume', '1038.HK')":970838
  },
  {
    "('Date', '')":"2025-08-13",
    "('Close', '1038.HK')":54.381690979,
    "('High', '1038.HK')":54.8254188902,
    "('Low', '1038.HK')":54.0365646728,
    "('Open', '1038.HK')":54.7268135236,
    "('Volume', '1038.HK')":1549264
  },
  {
    "('Date', '')":"2025-08-14",
    "('Close', '1038.HK')":53.5435295105,
    "('High', '1038.HK')":54.9733298739,
    "('Low', '1038.HK')":52.8532806701,
    "('Open', '1038.HK')":54.4802955252,
    "('Volume', '1038.HK')":2803100
  },
  {
    "('Date', '')":"2025-08-15",
    "('Close', '1038.HK')":52.8532829285,
    "('High', '1038.HK')":53.5435317984,
    "('Low', '1038.HK')":52.7546775591,
    "('Open', '1038.HK')":53.5435317984,
    "('Volume', '1038.HK')":2101037
  },
  {
    "('Date', '')":"2025-08-18",
    "('Close', '1038.HK')":52.3602485657,
    "('High', '1038.HK')":53.2477119359,
    "('Low', '1038.HK')":52.2616431963,
    "('Open', '1038.HK')":53.2477119359,
    "('Volume', '1038.HK')":2429723
  },
  {
    "('Date', '')":"2025-08-19",
    "('Close', '1038.HK')":51.7686080933,
    "('High', '1038.HK')":53.0504966842,
    "('Low', '1038.HK')":51.7193054093,
    "('Open', '1038.HK')":52.2616424561,
    "('Volume', '1038.HK')":1607936
  },
  {
    "('Date', '')":"2025-08-20",
    "('Close', '1038.HK')":51.7686080933,
    "('High', '1038.HK')":52.1137306426,
    "('Low', '1038.HK')":51.4727882279,
    "('Open', '1038.HK')":51.9165199067,
    "('Volume', '1038.HK')":2011984
  },
  {
    "('Date', '')":"2025-08-21",
    "('Close', '1038.HK')":52.1630363464,
    "('High', '1038.HK')":52.4588562076,
    "('Low', '1038.HK')":51.7686073572,
    "('Open', '1038.HK')":51.7686073572,
    "('Volume', '1038.HK')":1307912
  },
  {
    "('Date', '')":"2025-08-22",
    "('Close', '1038.HK')":51.916519165,
    "('High', '1038.HK')":52.4588562041,
    "('Low', '1038.HK')":51.8672127202,
    "('Open', '1038.HK')":52.1630363429,
    "('Volume', '1038.HK')":1539690
  },
  {
    "('Date', '')":"2025-08-25",
    "('Close', '1038.HK')":51.916519165,
    "('High', '1038.HK')":52.6560706987,
    "('Low', '1038.HK')":51.7686073537,
    "('Open', '1038.HK')":52.4588562041,
    "('Volume', '1038.HK')":2210657
  },
  {
    "('Date', '')":"2025-08-26",
    "('Close', '1038.HK')":51.9658241272,
    "('High', '1038.HK')":52.2616440013,
    "('Low', '1038.HK')":51.7686096239,
    "('Open', '1038.HK')":52.1137321835,
    "('Volume', '1038.HK')":2842384
  },
  {
    "('Date', '')":"2025-08-27",
    "('Close', '1038.HK')":51.3741798401,
    "('High', '1038.HK')":52.2616432105,
    "('Low', '1038.HK')":51.1276626551,
    "('Open', '1038.HK')":52.2123405259,
    "('Volume', '1038.HK')":3326754
  },
  {
    "('Date', '')":"2025-08-28",
    "('Close', '1038.HK')":51.4727897644,
    "('High', '1038.HK')":51.6700042677,
    "('Low', '1038.HK')":51.0783607578,
    "('Open', '1038.HK')":51.0783607578,
    "('Volume', '1038.HK')":1073985
  },
  {
    "('Date', '')":"2025-08-29",
    "('Close', '1038.HK')":51.5220909119,
    "('High', '1038.HK')":51.7193054093,
    "('Low', '1038.HK')":51.3248764144,
    "('Open', '1038.HK')":51.7193054093,
    "('Volume', '1038.HK')":1327728
  },
  {
    "('Date', '')":"2025-09-01",
    "('Close', '1038.HK')":51.8672142029,
    "('High', '1038.HK')":51.9165206491,
    "('Low', '1038.HK')":51.374179833,
    "('Open', '1038.HK')":51.6700034642,
    "('Volume', '1038.HK')":1310585
  },
  {
    "('Date', '')":"2025-09-02",
    "('Close', '1038.HK')":51.8672142029,
    "('High', '1038.HK')":52.1137313878,
    "('Low', '1038.HK')":51.6700034642,
    "('Open', '1038.HK')":51.8672142029,
    "('Volume', '1038.HK')":1716914
  },
  {
    "('Date', '')":"2025-09-03",
    "('Close', '1038.HK')":51.5713920593,
    "('High', '1038.HK')":52.163035534,
    "('Low', '1038.HK')":51.4234840118,
    "('Open', '1038.HK')":51.8672119159,
    "('Volume', '1038.HK')":1726308
  },
  {
    "('Date', '')":"2025-09-04",
    "('Close', '1038.HK')":51.5220909119,
    "('High', '1038.HK')":51.8672134612,
    "('Low', '1038.HK')":51.3741790984,
    "('Open', '1038.HK')":51.8179107772,
    "('Volume', '1038.HK')":958859
  },
  {
    "('Date', '')":"2025-09-05",
    "('Close', '1038.HK')":52.2123413086,
    "('High', '1038.HK')":52.2123413086,
    "('Low', '1038.HK')":51.5220924281,
    "('Open', '1038.HK')":51.5220924281,
    "('Volume', '1038.HK')":1107713
  },
  {
    "('Date', '')":"2025-09-08",
    "('Close', '1038.HK')":51.7686080933,
    "('High', '1038.HK')":52.2616424561,
    "('Low', '1038.HK')":51.5713935958,
    "('Open', '1038.HK')":52.2123397721,
    "('Volume', '1038.HK')":1362114
  },
  {
    "('Date', '')":"2025-09-09",
    "('Close', '1038.HK')":51.6700019836,
    "('High', '1038.HK')":51.9658218448,
    "('Low', '1038.HK')":51.472787489,
    "('Open', '1038.HK')":51.8179100334,
    "('Volume', '1038.HK')":2061039
  },
  {
    "('Date', '')":"2025-09-10",
    "('Close', '1038.HK')":51.6500015259,
    "('High', '1038.HK')":51.9000015259,
    "('Low', '1038.HK')":51.25,
    "('Open', '1038.HK')":51.5999984741,
    "('Volume', '1038.HK')":1754088
  },
  {
    "('Date', '')":"2025-09-11",
    "('Close', '1038.HK')":52.0,
    "('High', '1038.HK')":52.0499992371,
    "('Low', '1038.HK')":51.5,
    "('Open', '1038.HK')":51.5,
    "('Volume', '1038.HK')":1290088
  },
  {
    "('Date', '')":"2025-09-12",
    "('Close', '1038.HK')":52.5999984741,
    "('High', '1038.HK')":52.5999984741,
    "('Low', '1038.HK')":52.0999984741,
    "('Open', '1038.HK')":52.4500007629,
    "('Volume', '1038.HK')":976940
  },
  {
    "('Date', '')":"2025-09-15",
    "('Close', '1038.HK')":53.8499984741,
    "('High', '1038.HK')":54.25,
    "('Low', '1038.HK')":52.5,
    "('Open', '1038.HK')":52.5,
    "('Volume', '1038.HK')":3124008
  },
  {
    "('Date', '')":"2025-09-16",
    "('Close', '1038.HK')":54.0999984741,
    "('High', '1038.HK')":54.1500015259,
    "('Low', '1038.HK')":53.4000015259,
    "('Open', '1038.HK')":53.5,
    "('Volume', '1038.HK')":1292873
  },
  {
    "('Date', '')":"2025-09-17",
    "('Close', '1038.HK')":53.3499984741,
    "('High', '1038.HK')":54.4000015259,
    "('Low', '1038.HK')":53.2999992371,
    "('Open', '1038.HK')":54.0999984741,
    "('Volume', '1038.HK')":1555048
  },
  {
    "('Date', '')":"2025-09-18",
    "('Close', '1038.HK')":53.25,
    "('High', '1038.HK')":53.7999992371,
    "('Low', '1038.HK')":53.0999984741,
    "('Open', '1038.HK')":53.7999992371,
    "('Volume', '1038.HK')":988181
  },
  {
    "('Date', '')":"2025-09-19",
    "('Close', '1038.HK')":52.2000007629,
    "('High', '1038.HK')":53.6500015259,
    "('Low', '1038.HK')":52.0,
    "('Open', '1038.HK')":53.6500015259,
    "('Volume', '1038.HK')":2963137
  },
  {
    "('Date', '')":"2025-09-22",
    "('Close', '1038.HK')":52.1500015259,
    "('High', '1038.HK')":52.5,
    "('Low', '1038.HK')":52.0499992371,
    "('Open', '1038.HK')":52.4000015259,
    "('Volume', '1038.HK')":911108
  },
  {
    "('Date', '')":"2025-09-23",
    "('Close', '1038.HK')":52.1500015259,
    "('High', '1038.HK')":52.5,
    "('Low', '1038.HK')":52.0999984741,
    "('Open', '1038.HK')":52.1500015259,
    "('Volume', '1038.HK')":834973
  },
  {
    "('Date', '')":"2025-09-24",
    "('Close', '1038.HK')":51.9500007629,
    "('High', '1038.HK')":52.2999992371,
    "('Low', '1038.HK')":51.5999984741,
    "('Open', '1038.HK')":52.1500015259,
    "('Volume', '1038.HK')":2191634
  },
  {
    "('Date', '')":"2025-09-25",
    "('Close', '1038.HK')":51.2999992371,
    "('High', '1038.HK')":52.2000007629,
    "('Low', '1038.HK')":51.0999984741,
    "('Open', '1038.HK')":52.2000007629,
    "('Volume', '1038.HK')":2365709
  },
  {
    "('Date', '')":"2025-09-26",
    "('Close', '1038.HK')":51.2999992371,
    "('High', '1038.HK')":51.5999984741,
    "('Low', '1038.HK')":51.0499992371,
    "('Open', '1038.HK')":51.2999992371,
    "('Volume', '1038.HK')":1811460
  },
  {
    "('Date', '')":"2025-09-29",
    "('Close', '1038.HK')":51.3499984741,
    "('High', '1038.HK')":51.7999992371,
    "('Low', '1038.HK')":50.7999992371,
    "('Open', '1038.HK')":51.7999992371,
    "('Volume', '1038.HK')":1709407
  },
  {
    "('Date', '')":"2025-09-30",
    "('Close', '1038.HK')":51.0999984741,
    "('High', '1038.HK')":51.7000007629,
    "('Low', '1038.HK')":51.0499992371,
    "('Open', '1038.HK')":51.7000007629,
    "('Volume', '1038.HK')":1339472
  },
  {
    "('Date', '')":"2025-10-02",
    "('Close', '1038.HK')":51.7000007629,
    "('High', '1038.HK')":51.9000015259,
    "('Low', '1038.HK')":51.2000007629,
    "('Open', '1038.HK')":51.2000007629,
    "('Volume', '1038.HK')":1289848
  },
  {
    "('Date', '')":"2025-10-03",
    "('Close', '1038.HK')":52.1500015259,
    "('High', '1038.HK')":52.2000007629,
    "('Low', '1038.HK')":51.5999984741,
    "('Open', '1038.HK')":51.7000007629,
    "('Volume', '1038.HK')":1037841
  },
  {
    "('Date', '')":"2025-10-06",
    "('Close', '1038.HK')":51.4500007629,
    "('High', '1038.HK')":52.0499992371,
    "('Low', '1038.HK')":51.25,
    "('Open', '1038.HK')":52.0,
    "('Volume', '1038.HK')":633153
  },
  {
    "('Date', '')":"2025-10-08",
    "('Close', '1038.HK')":51.5,
    "('High', '1038.HK')":51.7999992371,
    "('Low', '1038.HK')":51.1500015259,
    "('Open', '1038.HK')":51.4000015259,
    "('Volume', '1038.HK')":946328
  },
  {
    "('Date', '')":"2025-10-09",
    "('Close', '1038.HK')":51.0,
    "('High', '1038.HK')":51.7000007629,
    "('Low', '1038.HK')":50.9500007629,
    "('Open', '1038.HK')":51.5,
    "('Volume', '1038.HK')":1785946
  },
  {
    "('Date', '')":"2025-10-10",
    "('Close', '1038.HK')":51.75,
    "('High', '1038.HK')":51.75,
    "('Low', '1038.HK')":50.9000015259,
    "('Open', '1038.HK')":51.0,
    "('Volume', '1038.HK')":1599510
  },
  {
    "('Date', '')":"2025-10-13",
    "('Close', '1038.HK')":51.3499984741,
    "('High', '1038.HK')":51.5,
    "('Low', '1038.HK')":50.75,
    "('Open', '1038.HK')":51.5,
    "('Volume', '1038.HK')":1282128
  },
  {
    "('Date', '')":"2025-10-14",
    "('Close', '1038.HK')":51.75,
    "('High', '1038.HK')":52.0,
    "('Low', '1038.HK')":50.9500007629,
    "('Open', '1038.HK')":51.3499984741,
    "('Volume', '1038.HK')":1717471
  },
  {
    "('Date', '')":"2025-10-15",
    "('Close', '1038.HK')":52.3499984741,
    "('High', '1038.HK')":52.4000015259,
    "('Low', '1038.HK')":51.75,
    "('Open', '1038.HK')":51.9000015259,
    "('Volume', '1038.HK')":2734550
  },
  {
    "('Date', '')":"2025-10-16",
    "('Close', '1038.HK')":52.5999984741,
    "('High', '1038.HK')":52.7000007629,
    "('Low', '1038.HK')":51.9500007629,
    "('Open', '1038.HK')":52.3499984741,
    "('Volume', '1038.HK')":1566046
  },
  {
    "('Date', '')":"2025-10-17",
    "('Close', '1038.HK')":52.9000015259,
    "('High', '1038.HK')":53.0,
    "('Low', '1038.HK')":52.2999992371,
    "('Open', '1038.HK')":52.6500015259,
    "('Volume', '1038.HK')":2457420
  },
  {
    "('Date', '')":"2025-10-20",
    "('Close', '1038.HK')":52.7999992371,
    "('High', '1038.HK')":53.25,
    "('Low', '1038.HK')":52.4500007629,
    "('Open', '1038.HK')":52.7999992371,
    "('Volume', '1038.HK')":1437263
  },
  {
    "('Date', '')":"2025-10-21",
    "('Close', '1038.HK')":52.25,
    "('High', '1038.HK')":53.0,
    "('Low', '1038.HK')":51.9000015259,
    "('Open', '1038.HK')":53.0,
    "('Volume', '1038.HK')":2589302
  },
  {
    "('Date', '')":"2025-10-22",
    "('Close', '1038.HK')":51.7000007629,
    "('High', '1038.HK')":52.4000015259,
    "('Low', '1038.HK')":51.5499992371,
    "('Open', '1038.HK')":52.2000007629,
    "('Volume', '1038.HK')":2161291
  },
  {
    "('Date', '')":"2025-10-23",
    "('Close', '1038.HK')":51.2000007629,
    "('High', '1038.HK')":51.75,
    "('Low', '1038.HK')":51.0999984741,
    "('Open', '1038.HK')":51.7000007629,
    "('Volume', '1038.HK')":2389978
  },
  {
    "('Date', '')":"2025-10-24",
    "('Close', '1038.HK')":51.9000015259,
    "('High', '1038.HK')":52.0,
    "('Low', '1038.HK')":51.1500015259,
    "('Open', '1038.HK')":51.5,
    "('Volume', '1038.HK')":2700378
  },
  {
    "('Date', '')":"2025-10-27",
    "('Close', '1038.HK')":51.3499984741,
    "('High', '1038.HK')":52.0999984741,
    "('Low', '1038.HK')":51.1500015259,
    "('Open', '1038.HK')":51.9000015259,
    "('Volume', '1038.HK')":1263585
  },
  {
    "('Date', '')":"2025-10-28",
    "('Close', '1038.HK')":51.4500007629,
    "('High', '1038.HK')":51.7999992371,
    "('Low', '1038.HK')":51.25,
    "('Open', '1038.HK')":51.5499992371,
    "('Volume', '1038.HK')":1812728
  },
  {
    "('Date', '')":"2025-10-30",
    "('Close', '1038.HK')":51.0,
    "('High', '1038.HK')":51.7999992371,
    "('Low', '1038.HK')":50.5,
    "('Open', '1038.HK')":51.7999992371,
    "('Volume', '1038.HK')":2978946
  },
  {
    "('Date', '')":"2025-10-31",
    "('Close', '1038.HK')":50.5499992371,
    "('High', '1038.HK')":51.0499992371,
    "('Low', '1038.HK')":50.5,
    "('Open', '1038.HK')":51.0,
    "('Volume', '1038.HK')":1909898
  },
  {
    "('Date', '')":"2025-11-03",
    "('Close', '1038.HK')":50.7999992371,
    "('High', '1038.HK')":50.7999992371,
    "('Low', '1038.HK')":50.2000007629,
    "('Open', '1038.HK')":50.5499992371,
    "('Volume', '1038.HK')":1937289
  },
  {
    "('Date', '')":"2025-11-04",
    "('Close', '1038.HK')":51.0,
    "('High', '1038.HK')":51.25,
    "('Low', '1038.HK')":50.6500015259,
    "('Open', '1038.HK')":50.7999992371,
    "('Volume', '1038.HK')":1273256
  },
  {
    "('Date', '')":"2025-11-05",
    "('Close', '1038.HK')":51.3499984741,
    "('High', '1038.HK')":51.3499984741,
    "('Low', '1038.HK')":50.75,
    "('Open', '1038.HK')":50.9500007629,
    "('Volume', '1038.HK')":1018768
  },
  {
    "('Date', '')":"2025-11-06",
    "('Close', '1038.HK')":52.1500015259,
    "('High', '1038.HK')":52.4000015259,
    "('Low', '1038.HK')":51.25,
    "('Open', '1038.HK')":51.3499984741,
    "('Volume', '1038.HK')":2452601
  },
  {
    "('Date', '')":"2025-11-07",
    "('Close', '1038.HK')":52.9500007629,
    "('High', '1038.HK')":52.9500007629,
    "('Low', '1038.HK')":52.0,
    "('Open', '1038.HK')":52.0,
    "('Volume', '1038.HK')":2555416
  },
  {
    "('Date', '')":"2025-11-10",
    "('Close', '1038.HK')":53.2999992371,
    "('High', '1038.HK')":53.4000015259,
    "('Low', '1038.HK')":52.9000015259,
    "('Open', '1038.HK')":52.9500007629,
    "('Volume', '1038.HK')":2135794
  },
  {
    "('Date', '')":"2025-11-11",
    "('Close', '1038.HK')":53.75,
    "('High', '1038.HK')":53.8499984741,
    "('Low', '1038.HK')":53.0999984741,
    "('Open', '1038.HK')":53.0999984741,
    "('Volume', '1038.HK')":2825142
  },
  {
    "('Date', '')":"2025-11-12",
    "('Close', '1038.HK')":54.0,
    "('High', '1038.HK')":54.2000007629,
    "('Low', '1038.HK')":53.5999984741,
    "('Open', '1038.HK')":53.7999992371,
    "('Volume', '1038.HK')":3461418
  },
  {
    "('Date', '')":"2025-11-13",
    "('Close', '1038.HK')":54.5,
    "('High', '1038.HK')":54.5,
    "('Low', '1038.HK')":53.8499984741,
    "('Open', '1038.HK')":54.0,
    "('Volume', '1038.HK')":2280352
  },
  {
    "('Date', '')":"2025-11-14",
    "('Close', '1038.HK')":54.25,
    "('High', '1038.HK')":54.6500015259,
    "('Low', '1038.HK')":54.0,
    "('Open', '1038.HK')":54.0,
    "('Volume', '1038.HK')":1862347
  }
]